sanic_gzip/__init__.py
test/__init__.py
test/test_decorator.py
sanic_gzip-0.4.1.dist-info/LICENSE
sanic_gzip-0.4.1.dist-info/METADATA
sanic_gzip-0.4.1.dist-info/WHEEL
sanic_gzip-0.4.1.dist-info/top_level.txt
sanic_gzip-0.4.1.dist-info/RECORD
