Metadata-Version: 2.1
Name: sanic-gzip
Version: 0.4.1
Summary: Add compress to Sanic response as decorator
Home-page: https://github.com/koug44/sanic-gzip
Author: Damien Alexandre
Author-email: damien.alexandre@muage.org
License: UNKNOWN
Platform: UNKNOWN
Classifier: Programming Language :: Python :: 3
Classifier: License :: OSI Approved :: MIT License
Requires-Python: >=3.6
License-File: LICENSE
Requires-Dist: sanic (>=21.12)
